shingram/__init__.py
shingram/bot.py
shingram/client.py
shingram/events.py
shingram/exceptions.py
shingram/py.typed
shingram/router.py
shingram/runtime.py
shingram/utils.py
shingram/webhook.py
shingram-0.3.0.dist-info/LICENSE
shingram-0.3.0.dist-info/METADATA
shingram-0.3.0.dist-info/WHEEL
shingram-0.3.0.dist-info/top_level.txt
shingram-0.3.0.dist-info/RECORD
