Metadata-Version: 2.1
Name: shingram
Version: 0.3.0
Summary: Minimal Python wrapper for the Telegram Bot API; one Event, one router, sync and async.
Author: Ren Nouzumoto
Maintainer: Ren Nouzumoto
Project-URL: Homepage, https://github.com/nouzumoto/shingram
Project-URL: Documentation, https://nouzumoto.github.io/shingram/
Project-URL: Repository, https://github.com/nouzumoto/shingram
Project-URL: Issues, https://github.com/nouzumoto/shingram/issues
Project-URL: Bug Tracker, https://github.com/nouzumoto/shingram/issues
Keywords: telegram,bot,api,wrapper,telegram-bot,telegram-api,shingram,minimal,lightweight
Classifier: Development Status :: 4 - Beta
Classifier: Intended Audience :: Developers
Classifier: License :: OSI Approved :: MIT License
Classifier: Operating System :: OS Independent
Classifier: Programming Language :: Python :: 3
Classifier: Programming Language :: Python :: 3.10
Classifier: Programming Language :: Python :: 3.11
Classifier: Programming Language :: Python :: 3.12
Classifier: Programming Language :: Python :: 3.13
Classifier: Topic :: Software Development :: Libraries :: Python Modules
Classifier: Topic :: Communications :: Chat
Requires-Python: >=3.10
License-File: LICENSE
Requires-Dist: httpx>=0.24.0
Provides-Extra: dev
Requires-Dist: pytest>=7.0.0; extra == "dev"
